scan_lan_clients.service
simplelanscan/__init__.py
simplelanscan/config.ini
simplelanscan/index.json
simplelanscan/scan.py
simplelanscan-0.1.9.dist-info/entry_points.txt
simplelanscan-0.1.9.dist-info/LICENSE
simplelanscan-0.1.9.dist-info/WHEEL
simplelanscan-0.1.9.dist-info/METADATA
simplelanscan-0.1.9.dist-info/RECORD
